<?xml version="1.0" encoding="windows-1251"?><posts><post><id>{7657B0FB-59C2-4B4E-99AB-AB99D4DF69E3}</id><score>1.00000000</score><lvl>0</lvl><root>{7657B0FB-59C2-4B4E-99AB-AB99D4DF69E3}</root><parent>{7657B0FB-59C2-4B4E-99AB-AB99D4DF69E3}</parent><create>2001-09-16T17:11:00</create><modify>2001-09-16T17:11:00</modify><url>http://dolboeb.livejournal.com/45041.html?format=light</url><store>2011-02-04T12:01:10.017</store><update>2011-02-04T12:01:10.017</update><author authorid="dolboeb" authorprofile="http://dolboeb.livejournal.com/profile" authoravatar="http://files.livejournal.com/userhead/20" authorhome="http://dolboeb.livejournal.com/" authorname="dolboeb">&lt;span lj:user="dolboeb"&gt;&lt;a href="http://dolboeb.livejournal.com/profile"&gt;&lt;img src="http://files.livejournal.com/userhead/20"&gt;&lt;/a&gt;&lt;a href="http://dolboeb.livejournal.com/"&gt;&lt;b&gt;dolboeb&lt;/b&gt;&lt;/a&gt;&lt;/span&gt;</author><title>Ирония судьбы, или без легкого пара</title><tags /><body>Сегодня день рождения у &lt;a href="http://www.livejournal.com/users/anikitin/" target="_blank"&gt;Никитина Антона Борисовича&lt;/a&gt;, сообщает напоминалка ЖЖ.&lt;br/&gt;Расти большой, тезка тезкович т.&lt;br/&gt;Поздравляю.&lt;br/&gt;&lt;br/&gt;Сегодня же день рождения у &lt;a href="http://www.livejournal.com/users/plushev/" target="_blank"&gt;Плющева Александра Владимировича&lt;/a&gt;, сообщает тот же источник. Обратно поздравляю.&lt;br/&gt;&lt;br/&gt;Что примечательно. У Никитина день рождения в 1968 году, а у Плющева - шестерка "жигулей" с тем же номером (по крайней мере, совсем недавно еще была, если он ее до сих пор Вике не подарил, не сдал в металлолом, или каким-нибудь иным способом не употребил во благо окружающему человечеству).&lt;br/&gt;&lt;br/&gt;Если бы еще у Никитина сыскалась какая-нибудь астральная связь с цифрой 1972 (явно не номер машины, они теперь трехзначные, но вдруг бы родня, офис или стратегические партнеры в соответствующей части Техаса) - вышло бы почти как с &lt;a href="http://www.generate74.com/pockett/presidents.html" target="_blank"&gt;Линкольном и Кеннеди&lt;/a&gt;. Даже если у них и &lt;a href="http://www.webpresidentsusa.com/AP070102.htm" target="_blank"&gt;не было&lt;/a&gt; соответствующих секретарей.</body></post><post><id>{AE462C49-A5F5-46A3-A52B-2FDE900AD588}</id><score>0.50000000</score><lvl>1</lvl><root>{7657B0FB-59C2-4B4E-99AB-AB99D4DF69E3}</root><parent>{7657B0FB-59C2-4B4E-99AB-AB99D4DF69E3}</parent><create>2001-10-04T05:00:00</create><modify>2001-10-04T05:00:00</modify><url>http://dolboeb.livejournal.com/45041.html?thread=201457&amp;format=light#t201457</url><store>2011-02-04T12:01:11.743</store><update>2011-02-04T12:01:11.743</update><author authorid="unregistered" authorprofile="http://unregistered.livejournal.com/profile" authoravatar="http://l-stat.livejournal.com/img/userinfo.gif?v=1" authorhome="http://unregistered.livejournal.com/" authorname="unregistered">&lt;span lj:user="unregistered"&gt;&lt;a href="http://unregistered.livejournal.com/profile"&gt;&lt;img src="http://l-stat.livejournal.com/img/userinfo.gif?v=1"&gt;&lt;/a&gt;&lt;a href="http://unregistered.livejournal.com/"&gt;&lt;b&gt;unregistered&lt;/b&gt;&lt;/a&gt;&lt;/span&gt;</author><title /><tags /><body>Вспоминается история-незабудка про калифорнийские CTO XYEB.</body></post></posts>